[
    {
        "%vlocity_namespace%__IsExclude__c": false,
        "%vlocity_namespace%__OverrideType__c": "Attribute",
        "%vlocity_namespace%__OverridingAttributeAssignmentCategoryId__c": {
            "%vlocity_namespace%__Code__c": "Atributos-Cov-Edificio",
            "VlocityDataPackType": "VlocityLookupMatchingKeyObject",
            "VlocityLookupRecordSourceKey": "%vlocity_namespace%__AttributeCategory__c/Atributos-Cov-Edificio",
            "VlocityRecordSObjectType": "%vlocity_namespace%__AttributeCategory__c"
        },
        "%vlocity_namespace%__OverridingAttributeAssignmentId__c": {
            "%vlocity_namespace%__AttributeId__r.%vlocity_namespace%__Code__c": "Edificio_Coaseguro",
            "%vlocity_namespace%__IsOverride__c": false,
            "%vlocity_namespace%__ObjectId__c": {
                "%vlocity_namespace%__GlobalKey__c": "f2c973cd-4abb-3672-9174-39c6e5bbf030",
                "VlocityDataPackType": "VlocityMatchingKeyObject",
                "VlocityMatchingRecordSourceKey": "Product2/f2c973cd-4abb-3672-9174-39c6e5bbf030",
                "VlocityRecordSObjectType": "Product2"
            },
            "%vlocity_namespace%__OverrideContext__c": "",
            "VlocityDataPackType": "VlocityMatchingKeyObject",
            "VlocityMatchingRecordSourceKey": "%vlocity_namespace%__AttributeAssignment__c/b17ea3e2-6e4e-71bc-9f09-abfd9fd75f79",
            "VlocityRecordSObjectType": "%vlocity_namespace%__AttributeAssignment__c"
        },
        "%vlocity_namespace%__ProductGroupKey__c": "e56b66a9-6303-1a2e-0158-4bb1ac364c05",
        "%vlocity_namespace%__ProductId__c": {
            "%vlocity_namespace%__GlobalKey__c": "f2c973cd-4abb-3672-9174-39c6e5bbf030",
            "VlocityDataPackType": "VlocityMatchingKeyObject",
            "VlocityMatchingRecordSourceKey": "Product2/f2c973cd-4abb-3672-9174-39c6e5bbf030",
            "VlocityRecordSObjectType": "Product2"
        },
        "Name": "OverrideDefinition",
        "VlocityDataPackType": "SObject",
        "VlocityRecordSObjectType": "%vlocity_namespace%__OverrideDefinition__c"
    },
    {
        "%vlocity_namespace%__IsExclude__c": false,
        "%vlocity_namespace%__OverrideType__c": "Attribute",
        "%vlocity_namespace%__OverridingAttributeAssignmentCategoryId__c": {
            "%vlocity_namespace%__Code__c": "Atributos-Cov-Edificio",
            "VlocityDataPackType": "VlocityLookupMatchingKeyObject",
            "VlocityLookupRecordSourceKey": "%vlocity_namespace%__AttributeCategory__c/Atributos-Cov-Edificio",
            "VlocityRecordSObjectType": "%vlocity_namespace%__AttributeCategory__c"
        },
        "%vlocity_namespace%__OverridingAttributeAssignmentId__c": {
            "%vlocity_namespace%__AttributeId__r.%vlocity_namespace%__Code__c": "Edificio_Deducible",
            "%vlocity_namespace%__IsOverride__c": false,
            "%vlocity_namespace%__ObjectId__c": {
                "%vlocity_namespace%__GlobalKey__c": "f2c973cd-4abb-3672-9174-39c6e5bbf030",
                "VlocityDataPackType": "VlocityMatchingKeyObject",
                "VlocityMatchingRecordSourceKey": "Product2/f2c973cd-4abb-3672-9174-39c6e5bbf030",
                "VlocityRecordSObjectType": "Product2"
            },
            "%vlocity_namespace%__OverrideContext__c": "",
            "VlocityDataPackType": "VlocityMatchingKeyObject",
            "VlocityMatchingRecordSourceKey": "%vlocity_namespace%__AttributeAssignment__c/a3ef087c-c1f6-e336-e3b4-c998e1d87720",
            "VlocityRecordSObjectType": "%vlocity_namespace%__AttributeAssignment__c"
        },
        "%vlocity_namespace%__ProductGroupKey__c": "e56b66a9-6303-1a2e-0158-4bb1ac364c05",
        "%vlocity_namespace%__ProductId__c": {
            "%vlocity_namespace%__GlobalKey__c": "f2c973cd-4abb-3672-9174-39c6e5bbf030",
            "VlocityDataPackType": "VlocityMatchingKeyObject",
            "VlocityMatchingRecordSourceKey": "Product2/f2c973cd-4abb-3672-9174-39c6e5bbf030",
            "VlocityRecordSObjectType": "Product2"
        },
        "Name": "OverrideDefinition",
        "VlocityDataPackType": "SObject",
        "VlocityRecordSObjectType": "%vlocity_namespace%__OverrideDefinition__c"
    },
    {
        "%vlocity_namespace%__IsExclude__c": false,
        "%vlocity_namespace%__OverrideType__c": "Attribute",
        "%vlocity_namespace%__OverridingAttributeAssignmentCategoryId__c": {
            "%vlocity_namespace%__Code__c": "TEEV_ATRIBUTOS",
            "VlocityDataPackType": "VlocityLookupMatchingKeyObject",
            "VlocityLookupRecordSourceKey": "%vlocity_namespace%__AttributeCategory__c/TEEV_ATRIBUTOS",
            "VlocityRecordSObjectType": "%vlocity_namespace%__AttributeCategory__c"
        },
        "%vlocity_namespace%__OverridingAttributeAssignmentId__c": {
            "%vlocity_namespace%__AttributeId__r.%vlocity_namespace%__Code__c": "TEEV_EDI_PR_ INFLACION",
            "%vlocity_namespace%__IsOverride__c": false,
            "%vlocity_namespace%__ObjectId__c": {
                "%vlocity_namespace%__GlobalKey__c": "f2c973cd-4abb-3672-9174-39c6e5bbf030",
                "VlocityDataPackType": "VlocityMatchingKeyObject",
                "VlocityMatchingRecordSourceKey": "Product2/f2c973cd-4abb-3672-9174-39c6e5bbf030",
                "VlocityRecordSObjectType": "Product2"
            },
            "%vlocity_namespace%__OverrideContext__c": "",
            "VlocityDataPackType": "VlocityMatchingKeyObject",
            "VlocityMatchingRecordSourceKey": "%vlocity_namespace%__AttributeAssignment__c/75c95f8a-28ce-a1a0-4692-8dabce2e44b8",
            "VlocityRecordSObjectType": "%vlocity_namespace%__AttributeAssignment__c"
        },
        "%vlocity_namespace%__ProductGroupKey__c": "e56b66a9-6303-1a2e-0158-4bb1ac364c05",
        "%vlocity_namespace%__ProductId__c": {
            "%vlocity_namespace%__GlobalKey__c": "f2c973cd-4abb-3672-9174-39c6e5bbf030",
            "VlocityDataPackType": "VlocityMatchingKeyObject",
            "VlocityMatchingRecordSourceKey": "Product2/f2c973cd-4abb-3672-9174-39c6e5bbf030",
            "VlocityRecordSObjectType": "Product2"
        },
        "Name": "OverrideDefinition",
        "VlocityDataPackType": "SObject",
        "VlocityRecordSObjectType": "%vlocity_namespace%__OverrideDefinition__c"
    },
    {
        "%vlocity_namespace%__IsExclude__c": false,
        "%vlocity_namespace%__OverrideType__c": "Attribute",
        "%vlocity_namespace%__OverridingAttributeAssignmentCategoryId__c": {
            "%vlocity_namespace%__Code__c": "TEEV_ATRIBUTOS",
            "VlocityDataPackType": "VlocityLookupMatchingKeyObject",
            "VlocityLookupRecordSourceKey": "%vlocity_namespace%__AttributeCategory__c/TEEV_ATRIBUTOS",
            "VlocityRecordSObjectType": "%vlocity_namespace%__AttributeCategory__c"
        },
        "%vlocity_namespace%__OverridingAttributeAssignmentId__c": {
            "%vlocity_namespace%__AttributeId__r.%vlocity_namespace%__Code__c": "TEEV_EDI_SA_ INFLACION",
            "%vlocity_namespace%__IsOverride__c": false,
            "%vlocity_namespace%__ObjectId__c": {
                "%vlocity_namespace%__GlobalKey__c": "f2c973cd-4abb-3672-9174-39c6e5bbf030",
                "VlocityDataPackType": "VlocityMatchingKeyObject",
                "VlocityMatchingRecordSourceKey": "Product2/f2c973cd-4abb-3672-9174-39c6e5bbf030",
                "VlocityRecordSObjectType": "Product2"
            },
            "%vlocity_namespace%__OverrideContext__c": "",
            "VlocityDataPackType": "VlocityMatchingKeyObject",
            "VlocityMatchingRecordSourceKey": "%vlocity_namespace%__AttributeAssignment__c/4a21b020-702b-67de-188c-49f50594ede2",
            "VlocityRecordSObjectType": "%vlocity_namespace%__AttributeAssignment__c"
        },
        "%vlocity_namespace%__ProductGroupKey__c": "e56b66a9-6303-1a2e-0158-4bb1ac364c05",
        "%vlocity_namespace%__ProductId__c": {
            "%vlocity_namespace%__GlobalKey__c": "f2c973cd-4abb-3672-9174-39c6e5bbf030",
            "VlocityDataPackType": "VlocityMatchingKeyObject",
            "VlocityMatchingRecordSourceKey": "Product2/f2c973cd-4abb-3672-9174-39c6e5bbf030",
            "VlocityRecordSObjectType": "Product2"
        },
        "Name": "OverrideDefinition",
        "VlocityDataPackType": "SObject",
        "VlocityRecordSObjectType": "%vlocity_namespace%__OverrideDefinition__c"
    },
    {
        "%vlocity_namespace%__IsExclude__c": false,
        "%vlocity_namespace%__OverrideType__c": "Attribute",
        "%vlocity_namespace%__ProductGroupKey__c": "e56b66a9-6303-1a2e-0158-4bb1ac364c05",
        "%vlocity_namespace%__ProductId__c": {
            "%vlocity_namespace%__GlobalKey__c": "f2c973cd-4abb-3672-9174-39c6e5bbf030",
            "VlocityDataPackType": "VlocityMatchingKeyObject",
            "VlocityMatchingRecordSourceKey": "Product2/f2c973cd-4abb-3672-9174-39c6e5bbf030",
            "VlocityRecordSObjectType": "Product2"
        },
        "Name": "OverrideDefinition",
        "VlocityDataPackType": "SObject",
        "VlocityRecordSObjectType": "%vlocity_namespace%__OverrideDefinition__c"
    }
]