[
    {
        "FilterOperator": "=",
        "GlobalKey": "ClbInsDRCreateQuoteAndQLI3461253152775907",
        "IsDisabled": true,
        "IsRequiredForUpsert": false,
        "IsUpsertKey": false,
        "MigrationValue": "FAKEMAPPING",
        "Name": "ClbInsDRCreateQuoteAndQLI",
        "OmniDataTransformationId": {
            "Name": "ClbInsDRCreateQuoteAndQLI",
            "VlocityDataPackType": "VlocityMatchingKeyObject",
            "VlocityMatchingRecordSourceKey": "OmniDataTransform/ClbInsDRCreateQuoteAndQLI",
            "VlocityRecordSObjectType": "OmniDataTransform"
        },
        "OutputCreationSequence": 1,
        "OutputFieldName": "Id",
        "OutputObjectName": "Quote",
        "VlocityDataPackType": "SObject",
        "VlocityRecordSObjectType": "OmniDataTransformItem"
    },
    {
        "FilterOperator": "=",
        "GlobalKey": "ClbInsDRCreateQuoteAndQLI34021823102657867",
        "IsDisabled": true,
        "IsRequiredForUpsert": false,
        "IsUpsertKey": false,
        "MigrationValue": "FAKEMAPPING",
        "Name": "ClbInsDRCreateQuoteAndQLI",
        "OmniDataTransformationId": {
            "Name": "ClbInsDRCreateQuoteAndQLI",
            "VlocityDataPackType": "VlocityMatchingKeyObject",
            "VlocityMatchingRecordSourceKey": "OmniDataTransform/ClbInsDRCreateQuoteAndQLI",
            "VlocityRecordSObjectType": "OmniDataTransform"
        },
        "OutputCreationSequence": 2,
        "OutputFieldName": "Id",
        "OutputObjectName": "QuoteLineItem",
        "VlocityDataPackType": "SObject",
        "VlocityRecordSObjectType": "OmniDataTransformItem"
    },
    {
        "FilterOperator": "=",
        "GlobalKey": "ClbInsDRCreateQuoteAndQLI9790120074242286",
        "IsDisabled": false,
        "IsRequiredForUpsert": false,
        "IsUpsertKey": false,
        "LinkedFieldName": "Id",
        "LinkedObjectSequence": 1,
        "MigrationValue": "FAKEMAPPING",
        "Name": "ClbInsDRCreateQuoteAndQLI",
        "OmniDataTransformationId": {
            "Name": "ClbInsDRCreateQuoteAndQLI",
            "VlocityDataPackType": "VlocityMatchingKeyObject",
            "VlocityMatchingRecordSourceKey": "OmniDataTransform/ClbInsDRCreateQuoteAndQLI",
            "VlocityRecordSObjectType": "OmniDataTransform"
        },
        "OutputCreationSequence": 2,
        "OutputFieldName": "QuoteId",
        "OutputObjectName": "QuoteLineItem",
        "VlocityDataPackType": "SObject",
        "VlocityRecordSObjectType": "OmniDataTransformItem"
    }
]