[
    {
        "%vlocity_namespace%__IsExclude__c": false,
        "%vlocity_namespace%__OverrideType__c": "Attribute",
        "%vlocity_namespace%__OverridingAttributeAssignmentCategoryId__c": {
            "%vlocity_namespace%__Code__c": "ATRIBUTOS_RAMO_VIDA_INDIVIDUAL",
            "VlocityDataPackType": "VlocityLookupMatchingKeyObject",
            "VlocityLookupRecordSourceKey": "%vlocity_namespace%__AttributeCategory__c/ATRIBUTOS_RAMO_VIDA_INDIVIDUAL",
            "VlocityRecordSObjectType": "%vlocity_namespace%__AttributeCategory__c"
        },
        "%vlocity_namespace%__OverridingAttributeAssignmentId__c": {
            "%vlocity_namespace%__AttributeId__r.%vlocity_namespace%__Code__c": "VIDA_IND_PR_FALLECIMIENTO",
            "%vlocity_namespace%__IsOverride__c": false,
            "%vlocity_namespace%__ObjectId__c": {
                "%vlocity_namespace%__GlobalKey__c": "e1db2aa7-65d8-92fb-7c8d-01d2ebede9c0",
                "VlocityDataPackType": "VlocityMatchingKeyObject",
                "VlocityMatchingRecordSourceKey": "Product2/e1db2aa7-65d8-92fb-7c8d-01d2ebede9c0",
                "VlocityRecordSObjectType": "Product2"
            },
            "%vlocity_namespace%__OverrideContext__c": "",
            "VlocityDataPackType": "VlocityMatchingKeyObject",
            "VlocityMatchingRecordSourceKey": "%vlocity_namespace%__AttributeAssignment__c/f13906fd-418d-a64c-b503-ac62590dd3bf",
            "VlocityRecordSObjectType": "%vlocity_namespace%__AttributeAssignment__c"
        },
        "%vlocity_namespace%__ProductGroupKey__c": "7edbe91e-4f82-645c-f8b1-36c5bc20e8b7",
        "%vlocity_namespace%__ProductId__c": {
            "%vlocity_namespace%__GlobalKey__c": "e1db2aa7-65d8-92fb-7c8d-01d2ebede9c0",
            "VlocityDataPackType": "VlocityMatchingKeyObject",
            "VlocityMatchingRecordSourceKey": "Product2/e1db2aa7-65d8-92fb-7c8d-01d2ebede9c0",
            "VlocityRecordSObjectType": "Product2"
        },
        "Name": "OverrideDefinition",
        "VlocityDataPackType": "SObject",
        "VlocityRecordSObjectType": "%vlocity_namespace%__OverrideDefinition__c"
    },
    {
        "%vlocity_namespace%__IsExclude__c": false,
        "%vlocity_namespace%__OverrideType__c": "Attribute",
        "%vlocity_namespace%__OverridingAttributeAssignmentCategoryId__c": {
            "%vlocity_namespace%__Code__c": "ATRIBUTOS_RAMO_VIDA_INDIVIDUAL",
            "VlocityDataPackType": "VlocityLookupMatchingKeyObject",
            "VlocityLookupRecordSourceKey": "%vlocity_namespace%__AttributeCategory__c/ATRIBUTOS_RAMO_VIDA_INDIVIDUAL",
            "VlocityRecordSObjectType": "%vlocity_namespace%__AttributeCategory__c"
        },
        "%vlocity_namespace%__OverridingAttributeAssignmentId__c": {
            "%vlocity_namespace%__AttributeId__r.%vlocity_namespace%__Code__c": "VIDA_IND_SA_FALLECIMIENTO",
            "%vlocity_namespace%__IsOverride__c": false,
            "%vlocity_namespace%__ObjectId__c": {
                "%vlocity_namespace%__GlobalKey__c": "e1db2aa7-65d8-92fb-7c8d-01d2ebede9c0",
                "VlocityDataPackType": "VlocityMatchingKeyObject",
                "VlocityMatchingRecordSourceKey": "Product2/e1db2aa7-65d8-92fb-7c8d-01d2ebede9c0",
                "VlocityRecordSObjectType": "Product2"
            },
            "%vlocity_namespace%__OverrideContext__c": "",
            "VlocityDataPackType": "VlocityMatchingKeyObject",
            "VlocityMatchingRecordSourceKey": "%vlocity_namespace%__AttributeAssignment__c/0d69e5da-6a26-c67b-3a27-9690f7a80846",
            "VlocityRecordSObjectType": "%vlocity_namespace%__AttributeAssignment__c"
        },
        "%vlocity_namespace%__ProductGroupKey__c": "7edbe91e-4f82-645c-f8b1-36c5bc20e8b7",
        "%vlocity_namespace%__ProductId__c": {
            "%vlocity_namespace%__GlobalKey__c": "e1db2aa7-65d8-92fb-7c8d-01d2ebede9c0",
            "VlocityDataPackType": "VlocityMatchingKeyObject",
            "VlocityMatchingRecordSourceKey": "Product2/e1db2aa7-65d8-92fb-7c8d-01d2ebede9c0",
            "VlocityRecordSObjectType": "Product2"
        },
        "Name": "OverrideDefinition",
        "VlocityDataPackType": "SObject",
        "VlocityRecordSObjectType": "%vlocity_namespace%__OverrideDefinition__c"
    },
    {
        "%vlocity_namespace%__IsExclude__c": false,
        "%vlocity_namespace%__OverrideType__c": "Attribute",
        "%vlocity_namespace%__ProductGroupKey__c": "7edbe91e-4f82-645c-f8b1-36c5bc20e8b7",
        "%vlocity_namespace%__ProductId__c": {
            "%vlocity_namespace%__GlobalKey__c": "e1db2aa7-65d8-92fb-7c8d-01d2ebede9c0",
            "VlocityDataPackType": "VlocityMatchingKeyObject",
            "VlocityMatchingRecordSourceKey": "Product2/e1db2aa7-65d8-92fb-7c8d-01d2ebede9c0",
            "VlocityRecordSObjectType": "Product2"
        },
        "Name": "OverrideDefinition",
        "VlocityDataPackType": "SObject",
        "VlocityRecordSObjectType": "%vlocity_namespace%__OverrideDefinition__c"
    }
]