{
    "IsActive": true,
    "IsOmniScriptEmbeddable": false,
    "Name": "CoveragesWithAdditionalFields",
    "OmniProcessId": {
        "Name": "clbIPEmisionDanos",
        "VlocityDataPackType": "VlocityMatchingKeyObject",
        "VlocityMatchingRecordSourceKey": "OmniProcess/ClbIns/EmisionDanos/Procedure",
        "VlocityRecordSObjectType": "OmniProcess"
    },
    "PropertySetConfig": {
        "actionMessage": "",
        "additionalChainableResponse": {
        },
        "additionalInput": {
        },
        "additionalOutput": {
        },
        "advancedMerge": false,
        "advancedMergeMap": [
        ],
        "allowMergeNulls": true,
        "chainOnStep": false,
        "disOnTplt": false,
        "dynamicOutputFields": "",
        "executionConditionalFormula": "",
        "failOnStepError": true,
        "failureConditionalFormula": "",
        "failureResponse": {
        },
        "filterListFormula": "",
        "hasPrimary": false,
        "label": "ListAction6",
        "mergeFields": [
        ],
        "mergeListsOrder": [
            "QuoteCoverages"
        ],
        "primaryListKey": "",
        "responseJSONNode": "",
        "responseJSONPath": "",
        "returnOnlyAdditionalOutput": false,
        "returnOnlyFailureResponse": false,
        "sendJSONNode": "",
        "sendJSONPath": "",
        "sendOnlyAdditionalInput": false,
        "show": null,
        "sortBy": [
        ],
        "sortInDescendingOrder": false,
        "updateFieldValue": {
            "claseBien": "=IF(name LIKE \"EDIFICIO\", \"001\", IF(name LIKE \"CONTENIDO\", \"002\", \"\"))",
            "codramocert": "=SUBSTRING(name, 0, 4)",
            "productCode": "=SUBSTRING(productCode, 0, 4)"
        },
        "useFormulas": true
    },
    "Type": "List Merge Action",
    "VlocityDataPackType": "SObject",
    "VlocityRecordSObjectType": "OmniProcessElement",
    "VlocityRecordSourceKey": "OmniProcessElement/OmniProcess/ClbIns/EmisionDanos/Procedure/CoveragesWithAdditionalFields"
}